stactools/esa_worldcover/__init__.py
stactools/esa_worldcover/commands.py
stactools/esa_worldcover/constants.py
stactools/esa_worldcover/metadata.py
stactools/esa_worldcover/stac.py
stactools_esa_worldcover-0.2.0.dist-info/LICENSE
stactools_esa_worldcover-0.2.0.dist-info/METADATA
stactools_esa_worldcover-0.2.0.dist-info/WHEEL
stactools_esa_worldcover-0.2.0.dist-info/top_level.txt
stactools_esa_worldcover-0.2.0.dist-info/RECORD
