Metadata-Version: 2.1
Name: stactools-esa-worldcover
Version: 0.2.0
Summary: stactools package for ESA WorldCover data
Home-page: https://github.com/stactools-packages/esa-worldcover
Author: Preston Hartzell
Author-email: preston.hartzell@gmail.com
Project-URL: Issues, https://github.com/stactools-packages/esa-worldcover/issues
Keywords: stactools,pystac,catalog,STAC,ESA,landcover
Classifier: Development Status :: 4 - Beta
Classifier: License :: OSI Approved :: Apache Software License
Classifier: Programming Language :: Python :: 3.8
Classifier: Programming Language :: Python :: 3.9
Classifier: Programming Language :: Python :: 3.10
Classifier: Programming Language :: Python :: 3.11
License-File: LICENSE
Requires-Dist: click (>=8.1.3)
Requires-Dist: pystac (>=1.7.0)
Requires-Dist: stactools (>=0.4.4)
Requires-Dist: rasterio (>=1.3.6)
Requires-Dist: Shapely (>=2.0.1)
